{
    "resource_pack_name": "family-customize",
    "texture_name": "atlas.items",
    "texture_data": {
        "thunder_sword": {
            "textures": "textures/items/thunder_sword"
        },
        "thunder_sword_revised": {
            "textures": "textures/items/thunder_sword_revised"
        },
        "immovable_rod": {
            "textures": "textures/items/immovable_rod"
        },
        "hayabusa_sword": {
            "textures": "textures/items/hayabusa_sword"
        },
        "immovable_stone": {
            "textures": "textures/items/immovable_stone"
        },
        "floating_feather": {
            "textures": "textures/items/floating_feather"
        },
        "shop_lock": {
            "textures": "textures/items/shop_lock"
        },
        "teleport_rod": {
            "textures": "textures/items/teleport_rod"
        },
        "sanma": {
            "textures": "textures/items/sanma"
        },
        "cooked_sanma": {
            "textures": "textures/items/cooked_sanma"
        },
        "thunder_stone": {
            "textures": "textures/items/thunder_stone"
        },
        "thunder_rod": {
            "textures": "textures/items/thunder_rod"
        },
        "explode_sword": {
            "textures": "textures/items/explode_sword"
        },
        "wind_rod": {
            "textures": "textures/items/wind_rod"
        },
        "wind_control_rod": {
            "textures": "textures/items/wind_control_rod"
        },
        "funnel_unit": {
            "textures": "textures/items/funnel_unit"
        },
        "wind_rod_revised": {
            "textures": "textures/items/wind_rod_revised"
        },
        "light_sword": {
            "textures": "textures/items/light_sword"
        }
    }
}